alpha2fasta/AMINOcode.py
alpha2fasta/DNAbits.py
alpha2fasta/__init__.py
alpha2fasta/fileEncode.py
alpha2fasta-1.448.dist-info/METADATA
alpha2fasta-1.448.dist-info/WHEEL
alpha2fasta-1.448.dist-info/top_level.txt
alpha2fasta-1.448.dist-info/RECORD
