Metadata-Version: 2.1
Name: alpha2fasta
Version: 1.448
Summary: Encode text written in natural language in a FASTA-based format
Home-page: UNKNOWN
Author: Diogo de Jesus Soares Machado
Author-email: diogomachado.bioinfo@gmail.com
License: UNKNOWN
Platform: UNKNOWN
Requires-Dist: numpy
Requires-Dist: unidecode
Requires-Dist: Biopython
